experiments/eda-lab-iverilog-vcd-wave/counter.v
// counter.v —— 两层层级的小设计：顶层 counter_top 里挂一个 baud_gen 子模块
// 故意多放内部信号，方便演示 $dumpvars 层级/范围控制对 VCD 大小的影响。

module baud_gen (
    input  wire        clk,
    input  wire        rst_n,
    input  wire [7:0]  div,
    output reg         tick
);
    reg [7:0] cnt;
    // 内部中间信号：全量 dump 时它们也会进 VCD
    wire [7:0] cnt_next = (cnt >= div) ? 8'd0 : cnt + 8'd1;
    wire       hit      = (cnt >= div);

    always @(posedge clk or negedge rst_n) begin
        if (!rst_n) begin
            cnt  <= 8'd0;
            tick <= 1'b0;
        end else begin
            cnt  <= cnt_next;
            tick <= hit;
        end
    end
endmodule

module counter_top (
    input  wire        clk,
    input  wire        rst_n,
    input  wire        en,
    output wire [7:0]  count,
    output wire        tick
);
    reg [7:0] cnt_r;
    // 内部统计信号：仿真过程可见、平时看波形很少关心
    reg [15:0] tick_total;
    reg [7:0]  div_cfg;

    baud_gen u_baud (
        .clk   (clk),
        .rst_n (rst_n),
        .div   (div_cfg),
        .tick  (tick)
    );

    assign count = cnt_r;

    always @(posedge clk or negedge rst_n) begin
        if (!rst_n) begin
            cnt_r      <= 8'd0;
            tick_total <= 16'd0;
            div_cfg    <= 8'd15;
        end else begin
            if (tick) begin
                tick_total <= tick_total + 16'd1;
                if (en) cnt_r <= cnt_r + 8'd1;
            end
        end
    end
endmodule

experiments/eda-lab-iverilog-vcd-wave/tb_full.v
// tb_full.v —— 全量 dump：$dumpvars 不带参数，把 TB 以下所有层级的所有信号都写进 VCD
`timescale 1ns/1ps
module tb_full;
    reg        clk = 0;
    reg        rst_n = 0;
    reg        en = 0;
    wire [7:0] count;
    wire       tick;

    counter_top dut (
        .clk   (clk),
        .rst_n (rst_n),
        .en    (en),
        .count (count),
        .tick  (tick)
    );

    always #5 clk = ~clk;   // 100MHz

    integer i;
    initial begin
        $dumpfile("full.vcd");
        $dumpvars;          // 无参数 = 全层级全信号
        repeat (4) @(negedge clk);
        rst_n = 1;
        en = 1;
        // 跑 20000 个时钟，制造足够多的跳变
        for (i = 0; i < 20000; i = i + 1) @(negedge clk);
        $dumpflush;
        $display("FULL DONE count=%0d", count);
        $finish;
    end
endmodule

experiments/eda-lab-iverilog-vcd-wave/full.vcd
$date
	Wed Oct  7 14:58:20 2026
$end
$version
	Icarus Verilog
$end
$timescale
	1ps
$end
$scope module tb_full $end
$var wire 1 ! tick $end
$var wire 8 " count [7:0] $end
$var reg 1 # clk $end
$var reg 1 $ en $end
$var reg 1 % rst_n $end
$var integer 32 & i [31:0] $end
$scope module dut $end
$var wire 1 # clk $end
$var wire 8 ' count [7:0] $end
$var wire 1 $ en $end
$var wire 1 % rst_n $end
$var wire 1 ! tick $end
$var reg 8 ( cnt_r [7:0] $end
$var reg 8 ) div_cfg [7:0] $end
$var reg 16 * tick_total [15:0] $end
$scope module u_baud $end
$var wire 1 # clk $end
$var wire 8 + div [7:0] $end
$var wire 1 % rst_n $end
$var wire 1 , hit $end
$var wire 8 - cnt_next [7:0] $end
$var reg 8 . cnt [7:0] $end
$var reg 1 ! tick $end
$upscope $end
$upscope $end
$upscope $end
$enddefinitions $end
$comment Show the parameter values. $end
$dumpall
$end
#0
$dumpvars
bx .
bx -
x,
bx +
bx *
bx )
bx (
bx '
bx &
0%
0$
0#
bx "
x!
$end
#5000
b1 -
0!
0,
b0 .
b1111 )
b1111 +
b0 *
b0 "
b0 '
b0 (
1#
#10000
0#
#15000
1#
#20000
0#
#25000
1#
#30000
0#
#35000
1#
#40000
b0 &
1$
1%
0#
#45000
b10 -
b1 .
1#
#50000
b1 &
0#
#55000
b11 -
b10 .
1#
#60000
b10 &
0#
#65000
b100 -
b11 .
1#
#70000
b11 &
0#
#75000
b101 -
b100 .
1#
#80000
b100 &
0#
#85000
b110 -
b101 .
1#
#90000
b101 &
0#
#95000
b111 -
b110 .
1#
#100000
b110 &
0#
#105000
b1000 -
b111 .
1#
#110000
b111 &
0#
#115000
b1001 -
b1000 .
1#
#120000
b1000 &
0#
#125000
b1010 -
b1001 .
1#
#130000
b1001 &
0#
#135000
b1011 -
b1010 .
1#
#140000
b1010 &
0#
#145000
b1100 -
b1011 .
1#
#150000
b1011 &
0#
#155000
b1101 -
b1100 .
1#
#160000
b1100 &
0#
#165000
b1110 -
b1101 .
1#
#170000
b1101 &
0#
#175000
b1111 -
b1110 .
1#
#180000
b1110 &
0#
#185000
b0 -
1,
b1111 .
1#
#190000
b1111 &
0#
#195000
b1 -
1!
0,
b0 .
1#
#200000
b10000 &
0#
#205000
b10 -
0!
b1 .
b1 "
b1 '
b1 (
b1 *
1#
#210000
b10001 &
0#
#215000
b11 -
b10 .
1#
#220000
b10010 &
0#
#225000
b100 -
b11 .
1#
#230000
b10011 &
0#
#235000
b101 -
b100 .
1#
#240000
b10100 &
0#
#245000
b110 -
b101 .
1#
#250000
b10101 &
0#
#255000
b111 -
b110 .
1#
#260000
b10110 &
0#
#265000
b1000 -
b111 .
1#
#270000
b10111 &
0#
#275000
b1001 -
b1000 .
1#
#280000
b11000 &
0#
#285000
b1010 -
b1001 .
1#
#290000
b11001 &
0#
#295000
b1011 -
b1010 .
1#
#300000
b11010 &
0#
#305000
b1100 -
b1011 .
1#
#310000
b11011 &
0#
#315000
b1101 -
b1100 .
1#
#320000
b11100 &
0#
#325000
b1110 -
b1101 .
1#
#330000
b11101 &
0#
#335000
b1111 -
b1110 .
1#
#340000
b11110 &
0#
#345000
b0 -
1,
b1111 .
1#
#350000
b11111 &
0#
#355000
b1 -
1!
0,
b0 .
1#
#360000
b100000 &
0#
#365000
b10 -
0!
b1 .
b10 "
b10 '
b10 (
b10 *
1#
#370000
b100001 &
0#
#375000
b11 -
b10 .
1#
#380000
b100010 &
0#
#385000
b100 -
b11 .
1#
#390000
b100011 &
0#
#395000
b101 -
b100 .
1#
#400000
b100100 &
0#
#405000
b110 -
b101 .
1#
#410000
b100101 &
0#
#415000
b111 -
b110 .
1#
#420000
b100110 &
0#
#425000
b1000 -
b111 .
1#
#430000
b100111 &
0#
#435000
b1001 -
b1000 .
1#
#440000
b101000 &
0#
#445000
b1010 -
b1001 .
1#
#450000
b101001 &
0#
#455000
b1011 -
b1010 .
1#
#460000
b101010 &
0#
#465000
b1100 -
b1011 .
1#
#470000
b101011 &
0#
#475000
b1101 -
b1100 .
1#
#480000
b101100 &
0#
#485000
b1110 -
b1101 .
1#
#490000
b101101 &
0#
#495000
b1111 -
b1110 .
1#
#500000
b101110 &
0#
#505000
b0 -
1,
b1111 .
1#
#510000
b101111 &
0#
#515000
b1 -
1!
0,
b0 .
1#
#520000
b110000 &
0#
#525000
b10 -
0!
b1 .
b11 "
b11 '
b11 (
b11 *
1#
#530000
b110001 &
0#
#535000
b11 -
b10 .
1#
#540000
b110010 &
0#
#545000
b100 -
b11 .
1#
#550000
b110011 &
0#
#555000
b101 -
b100 .
1#
#560000
b110100 &
0#
#565000
b110 -
b101 .
1#
#570000
b110101 &
0#
#575000
b111 -
b110 .
1#
#580000
b110110 &
0#
#585000
b1000 -
b111 .
1#
#590000
b110111 &
0#
#595000
b1001 -
b1000 .
1#
#600000
b111000 &
0#
#605000
b1010 -
b1001 .
1#
#610000
b111001 &
0#
#615000
b1011 -
b1010 .
1#
#620000
b111010 &
0#
#625000
b1100 -
b1011 .
1#
#630000
b111011 &
0#
#635000
b1101 -
b1100 .
1#
#640000
b111100 &
0#
#645000
b1110 -
b1101 .
1#
#650000
b111101 &
0#
#655000
b1111 -
b1110 .
1#
#660000
b111110 &
0#
#665000
b0 -
1,
b1111 .
1#
#670000
b111111 &
0#
#675000
b1 -
1!
0,
b0 .
1#
#680000
b1000000 &
0#
#685000
b10 -
0!
b1 .
b100 "
b100 '
b100 (
b100 *
1#
#690000
b1000001 &
0#
#695000
b11 -
b10 .
1#
#700000
b1000010 &
0#
#705000
b100 -
b11 .
1#
#710000
b1000011 &
0#
#715000
b101 -
b100 .
1#
#720000
b1000100 &
0#
#725000
b110 -
b101 .
1#
#730000
b1000101 &
0#
#735000
b111 -
b110 .
1#
#740000
b1000110 &
0#
#745000
b1000 -
b111 .
1#
#750000
b1000111 &
0#
#755000
b1001 -
b1000 .
1#
#760000
b1001000 &
0#
#765000
b1010 -
b1001 .
1#
#770000
b1001001 &
0#
#775000
b1011 -
b1010 .
1#
#780000
b1001010 &
0#
#785000
b1100 -
b1011 .
1#
#790000
b1001011 &
0#
#795000
b1101 -
b1100 .
1#
#800000
b1001100 &
0#
#805000
b1110 -
b1101 .
1#
#810000
b1001101 &
0#
#815000
b1111 -
b1110 .
1#
#820000
b1001110 &
0#
#825000
b0 -
1,
b1111 .
1#
#830000
b1001111 &
0#
#835000
b1 -
1!
0,
b0 .
1#
#840000
b1010000 &
0#
#845000
b10 -
0!
b1 .
b101 "
b101 '
b101 (
b101 *
1#
#850000
b1010001 &
0#
#855000
b11 -
b10 .
1#
#860000
b1010010 &
0#
#865000
b100 -
b11 .
1#
#870000
b1010011 &
0#
#875000
b101 -
b100 .
1#
#880000
b1010100 &
0#
#885000
b110 -
b101 .
1#
#890000
b1010101 &
0#
#895000
b111 -
b110 .
1#
#900000
b1010110 &
0#
#905000
b1000 -
b111 .
1#
#910000
b1010111 &
0#
#915000
b1001 -
b1000 .
1#
#920000
b1011000 &
0#
#925000
b1010 -
b1001 .
1#
#930000
b1011001 &
0#
#935000
b1011 -
b1010 .
1#
#940000
b1011010 &
0#
#945000
b1100 -
b1011 .
1#
#950000
b1011011 &
0#
#955000
b1101 -
b1100 .
1#
#960000
b1011100 &
0#
#965000
b1110 -
b1101 .
1#
#970000
b1011101 &
0#
#975000
b1111 -
b1110 .
1#
#980000
b1011110 &
0#
#985000
b0 -
1,
b1111 .
1#
#990000
b1011111 &
0#
#995000
b1 -
1!
0,
b0 .
1#
#1000000
b1100000 &
0#
#1005000
b10 -
0!
b1 .
b110 "
b110 '
b110 (
b110 *
1#
#1010000
b1100001 &
0#
#1015000
b11 -
b10 .
1#
#1020000
b1100010 &
0#
#1025000
b100 -
b11 .
1#
#1030000
b1100011 &
0#
#1035000
b101 -
b100 .
1#
#1040000
b1100100 &
0#
#1045000
b110 -
b101 .
1#
#1050000
b1100101 &
0#
#1055000
b111 -
b110 .
1#
#1060000
b1100110 &
0#
#1065000
b1000 -
b111 .
1#
#1070000
b1100111 &
0#
#1075000
b1001 -
b1000 .
1#
#1080000
b1101000 &
0#
#1085000
b1010 -
b1001 .
1#
#1090000
b1101001 &
0#
#1095000
b1011 -
b1010 .
1#
#1100000
b1101010 &
0#
#1105000
b1100 -
b1011 .
1#
#1110000
b1101011 &
0#
#1115000
b1101 -
b1100 .
1#
#1120000
b1101100 &
0#
#1125000
b1110 -
b1101 .
1#
#1130000
b1101101 &
0#
#1135000
b1111 -
b1110 .
1#
#1140000
b1101110 &
0#
#1145000
b0 -
1,
b1111 .
1#
#1150000
b1101111 &
0#
#1155000
b1 -
1!
0,
b0 .
1#
#1160000
b1110000 &
0#
#1165000
b10 -
0!
b1 .
b111 "
b111 '
b111 (
b111 *
1#
#1170000
b1110001 &
0#
#1175000
b11 -
b10 .
1#
#1180000
b1110010 &
0#
#1185000
b100 -
b11 .
1#
#1190000
b1110011 &
0#
#1195000
b101 -
b100 .
1#
#1200000
b1110100 &
0#
#1205000
b110 -
b101 .
1#
#1210000
b1110101 &
0#
#1215000
b111 -
b110 .
1#
#1220000
b1110110 &
0#
#1225000
b1000 -
b111 .
1#
#1230000
b1110111 &
0#
#1235000
b1001 -
b1000 .
1#
#1240000
b1111000 &
0#
#1245000
b1010 -
b1001 .
1#
#1250000
b1111001 &
0#
#1255000
b1011 -
b1010 .
1#
#1260000
b1111010 &
0#
#1265000
b1100 -
b1011 .
1#
#1270000
b1111011 &
0#
#1275000
b1101 -
b1100 .
1#
#1280000
b1111100 &
0#
#1285000
b1110 -
b1101 .
1#
#1290000
b1111101 &
0#
#1295000
b1111 -
b1110 .
1#
#1300000
b1111110 &
0#
#1305000
b0 -
1,
b1111 .
1#
#1310000
b1111111 &
0#
#1315000
b1 -
1!
0,
b0 .
1#
#1320000
b10000000 &
0#
#1325000
b10 -
0!
b1 .
b1000 "
b1000 '
b1000 (
b1000 *
1#
#1330000
b10000001 &
0#
#1335000
b11 -
b10 .
1#
#1340000
b10000010 &
0#
#1345000
b100 -
b11 .
1#
#1350000
b10000011 &
0#
#1355000
b101 -
b100 .
1#
#1360000
b10000100 &
0#
#1365000
b110 -
b101 .
1#
#1370000
b10000101 &
0#
#1375000
b111 -
b110 .
1#
#1380000
b10000110 &
0#
#1385000
b1000 -
b111 .
1#
#1390000
b10000111 &
0#
#1395000
b1001 -
b1000 .
1#
#1400000
b10001000 &
0#
#1405000
b1010 -
b1001 .
1#
#1410000
b10001001 &
0#
#1415000
b1011 -
b1010 .
1#
#1420000
b10001010 &
0#
#1425000
b1100 -
b1011 .
1#
#1430000
b10001011 &
0#
#1435000
b1101 -
b1100 .
1#
#1440000
b10001100 &
0#
#1445000
b1110 -
b1101 .
1#
#1450000
b10001101 &
0#
#1455000
b1111 -
b1110 .
1#
#1460000
b10001110 &
0#
#1465000
b0 -
1,
b1111 .
1#
#1470000
b10001111 &
0#
#1475000
b1 -
1!
0,
b0 .
1#
#1480000
b10010000 &
0#
#1485000
b10 -
0!
b1 .
b1001 "
b1001 '
b1001 (
b1001 *
1#
#1490000
b10010001 &
0#
#1495000
b11 -
b10 .
1#
#1500000
b10010010 &
0#
#1505000
b100 -
b11 .
1#
#1510000
b10010011 &
0#
#1515000
b101 -
b100 .
1#
#1520000
b10010100 &
0#
#1525000
b110 -
b101 .
1#
#1530000
b10010101 &
0#
#1535000
b111 -
b110 .
1#
#1540000
b10010110 &
0#
#1545000
b1000 -
b111 .
1#
#1550000
b10010111 &
0#
#1555000
b1001 -
b1000 .
1#
#1560000
b10011000 &
0#
#1565000
b1010 -
b1001 .
1#
#1570000
b10011001 &
0#
#1575000
b1011 -
b1010 .
1#
#1580000
b10011010 &
0#
#1585000
b1100 -
b1011 .
1#
#1590000
b10011011 &
0#
#1595000
b1101 -
b1100 .
1#
#1600000
b10011100 &
0#
#1605000
b1110 -
b1101 .
1#
#1610000
b10011101 &
0#
#1615000
b1111 -
b1110 .
1#
#1620000
b10011110 &
0#
#1625000
b0 -
1,
b1111 .
1#
#1630000
b10011111 &
0#
#1635000
b1 -
1!
0,
b0 .
1#
#1640000
b10100000 &
0#
#1645000
b10 -
0!
b1 .
b1010 "
b1010 '
b1010 (
b1010 *
1#
#1650000
b10100001 &
0#
#1655000
b11 -
b10 .
1#
#1660000
b10100010 &
0#
#1665000
b100 -
b11 .
1#
#1670000
b10100011 &
0#
#1675000
b101 -
b100 .
1#
#1680000
b10100100 &
0#
#1685000
b110 -
b101 .
1#
#1690000
b10100101 &
0#
#1695000
b111 -
b110 .
1#
#1700000
b10100110 &
0#
#1705000
b1000 -
b111 .
1#
#1710000
b10100111 &
0#
#1715000
b1001 -
b1000 .
1#
#1720000
b10101000 &
0#
#1725000
b1010 -
b1001 .
1#
#1730000
b10101001 &
0#
#1735000
b1011 -
b1010 .
1#
#1740000
b10101010 &
0#
#1745000
b1100 -
b1011 .
1#
#1750000
b10101011 &
0#
#1755000
b1101 -
b1100 .
1#
#1760000
b10101100 &
0#
#1765000
b1110 -
b1101 .
1#
#1770000
b10101101 &
0#
#1775000
b1111 -
b1110 .
1#
#1780000
b10101110 &
0#
#1785000
b0 -
1,
b1111 .
1#
#1790000
b10101111 &
0#
#1795000
b1 -
1!
0,
b0 .
1#
#1800000
b10110000 &
0#
#1805000
b10 -
0!
b1 .
b1011 "
b1011 '
b1011 (
b1011 *
1#
#1810000
b10110001 &
0#
#1815000
b11 -
b10 .
1#
#1820000
b10110010 &
0#
#1825000
b100 -
b11 .
1#
#1830000
b10110011 &
0#
#1835000
b101 -
b100 .
1#
#1840000
b10110100 &
0#
#1845000
b110 -
b101 .
1#
#1850000
b10110101 &
0#
#1855000
b111 -
b110 .
1#
#1860000
b10110110 &
0#
#1865000
b1000 -
b111 .
1#
#1870000
b10110111 &
0#
#1875000
b1001 -
b1000 .
1#
#1880000
b10111000 &
0#
#1885000
b1010 -
b1001 .
1#
#1890000
b10111001 &
0#
#1895000
b1011 -
b1010 .
1#
#1900000
b10111010 &
0#
#1905000
b1100 -
b1011 .
1#
#1910000
b10111011 &
0#
#1915000
b1101 -
b1100 .
1#
#1920000
b10111100 &
0#
#1925000
b1110 -
b1101 .
1#
#1930000
b10111101 &
0#
#1935000
b1111 -
b1110 .
1#
#1940000
b10111110 &
0#
#1945000
b0 -
1,
b1111 .
1#
#1950000
b10111111 &
0#
#1955000
b1 -
1!
0,
b0 .
1#
#1960000
b11000000 &
0#
#1965000
b10 -
0!
b1 .
b1100 "
b1100 '
b1100 (
b1100 *
1#
#1970000
b11000001 &
0#
#1975000
b11 -
b10 .
1#
#1980000
b11000010 &
0#
#1985000
b100 -
b11 .
1#
#1990000
b11000011 &
0#
#1995000
b101 -
b100 .
1#
#2000000
b11000100 &
0#
#2005000
b110 -
b101 .
1#
#2010000
b11000101 &
0#
#2015000
b111 -
b110 .
1#
#2020000
b11000110 &
0#
#2025000
b1000 -
b111 .
1#
#2030000
b11000111 &
0#
#2035000
b1001 -
b1000 .
1#
#2040000
b11001000 &
0#
#2045000
b1010 -
b1001 .
1#
#2050000
b11001001 &
0#
#2055000
b1011 -
b1010 .
1#
#2060000
b11001010 &
0#
#2065000
b1100 -
b1011 .
1#
#2070000
b11001011 &
0#
#2075000
b1101 -
b1100 .
1#
#2080000
b11001100 &
0#
#2085000
b1110 -
b1101 .
1#
#2090000
b11001101 &
0#
#2095000
b1111 -
b1110 .
1#
#2100000
b11001110 &
0#
#2105000
b0 -
1,
b1111 .
1#
#2110000
b11001111 &
0#
#2115000
b1 -
1!
0,
b0 .
1#
#2120000
b11010000 &
0#
#2125000
b10 -
0!
b1 .
b1101 "
b1101 '
b1101 (
b1101 *
1#
#2130000
b11010001 &
0#
#2135000
b11 -
b10 .
1#
#2140000
b11010010 &
0#
#2145000
b100 -
b11 .
1#
#2150000
b11010011 &
0#
#2155000
b101 -
b100 .
1#
#2160000
b11010100 &
0#
#2165000
b110 -
b101 .
1#
#2170000
b11010101 &
0#
#2175000
b111 -
b110 .
1#
#2180000
b11010110 &
0#
#2185000
b1000 -
b111 .
1#
#2190000
b11010111 &
0#
#2195000
b1001 -
b1000 .
1#
#2200000
b11011000 &
0#
#2205000
b1010 -
b1001 .
1#
#2210000
b11011001 &
0#
#2215000
b1011 -
b1010 .
1#
#2220000
b11011010 &
0#
#2225000
b1100 -
b1011 .
1#
#2230000
b11011011 &
0#
#2235000
b1101 -
b1100 .
1#
#2240000
b11011100 &
0#
#2245000
b1110 -
b1101 .
1#
#2250000
b11011101 &
0#
#2255000
b1111 -
b1110 .
1#
#2260000
b11011110 &
0#
#2265000
b0 -
1,
b1111 .
1#
#2270000
b11011111 &
0#
#2275000
b1 -
1!
0,
b0 .
1#
#2280000
b11100000 &
0#
#2285000
b10 -
0!
b1 .
b1110 "
b1110 '
b1110 (
b1110 *
1#
#2290000
b11100001 &
0#
#2295000
b11 -
b10 .
1#
#2300000
b11100010 &
0#
#2305000
b100 -
b11 .
1#
#2310000
b11100011 &
0#
#2315000
b101 -
b100 .
1#
#2320000
b11100100 &
0#
#2325000
b110 -
b101 .
1#
#2330000
b11100101 &
0#
#2335000
b111 -
b110 .
1#
#2340000
b11100110 &
0#
#2345000
b1000 -
b111 .
1#
#2350000
b11100111 &
0#
#2355000
b1001 -
b1000 .
1#
#2360000
b11101000 &
0#
#2365000
b1010 -
b1001 .
1#
#2370000
b11101001 &
0#
#2375000
b1011 -
b1010 .
1#
#2380000
b11101010 &
0#
#2385000
b1100 -
b1011 .
1#
#2390000
b11101011 &
0#
#2395000
b1101 -
b1100 .
1#
#2400000
b11101100 &
0#
#2405000
b1110 -
b1101 .
1#
#2410000
b11101101 &
0#
#2415000
b1111 -
b1110 .
1#
#2420000
b11101110 &
0#
#2425000
b0 -
1,
b1111 .
1#
#2430000
b11101111 &
0#
#2435000
b1 -
1!
0,
b0 .
1#
#2440000
b11110000 &
0#
#2445000
b10 -
0!
b1 .
b1111 "
b1111 '
b1111 (
b1111 *
1#
#2450000
b11110001 &
0#
#2455000
b11 -
b10 .
1#
#2460000
b11110010 &
0#
#2465000
b100 -
b11 .
1#
#2470000
b11110011 &
0#
#2475000
b101 -
b100 .
1#
#2480000
b11110100 &
0#
#2485000
b110 -
b101 .
1#
#2490000
b11110101 &
0#
#2495000
b111 -
b110 .
1#
#2500000
b11110110 &
0#
#2505000
b1000 -
b111 .
1#
#2510000
b11110111 &
0#
#2515000
b1001 -
b1000 .
1#
#2520000
b11111000 &
0#
#2525000
b1010 -
b1001 .
1#
#2530000
b11111001 &
0#
#2535000
b1011 -
b1010 .
1#
#2540000
b11111010 &
0#
#2545000
b1100 -
b1011 .
1#
#2550000
b11111011 &
0#
#2555000
b1101 -
b1100 .
1#
#2560000
b11111100 &
0#
#2565000
b1110 -
b1101 .
1#
#2570000
b11111101 &
0#
#2575000
b1111 -
b1110 .
1#
#2580000
b11111110 &
0#
#2585000
b0 -
1,
b1111 .
1#
#2590000
b11111111 &
0#
#2595000
b1 -
1!
0,
b0 .
1#
#2600000
b100000000 &
0#
#2605000
b10 -
0!
b1 .
b10000 "
b10000 '
b10000 (
b10000 *
1#
#2610000
b100000001 &
0#
#2615000
b11 -
b10 .
1#
#2620000
b100000010 &
0#
#2625000
b100 -
b11 .
1#
#2630000
b100000011 &
0#
#2635000
b101 -
b100 .
1#
#2640000
b100000100 &
0#
#2645000
b110 -
b101 .
1#
#2650000
b100000101 &
0#
#2655000
b111 -
b110 .
1#
#2660000
b100000110 &
0#
#2665000
b1000 -
b111 .
1#
#2670000
b100000111 &
0#
#2675000
b1001 -
b1000 .
1#
#2680000
b100001000 &
0#
#2685000
b1010 -
b1001 .
1#
#2690000
b100001001 &
0#
#2695000
b1011 -
b1010 .
1#
#2700000
b100001010 &
0#
#2705000
b1100 -
b1011 .
1#
#2710000
b100001011 &
0#
#2715000
b1101 -
b1100 .
1#
#2720000
b100001100 &
0#
#2725000
b1110 -
b1101 .
1#
#2730000
b100001101 &
0#
#2735000
b1111 -
b1110 .
1#
#2740000
b100001110 &
0#
#2745000
b0 -
1,
b1111 .
1#
#2750000
b100001111 &
0#
#2755000
b1 -
1!
0,
b0 .
1#
#2760000
b100010000 &
0#
#2765000
b10 -
0!
b1 .
b10001 "
b10001 '
b10001 (
b10001 *
1#
#2770000
b100010001 &
0#
#2775000
b11 -
b10 .
1#
#2780000
b100010010 &
0#
#2785000
b100 -
b11 .
1#
#2790000
b100010011 &
0#
#2795000
b101 -
b100 .
1#
#2800000
b100010100 &
0#
#2805000
b110 -
b101 .
1#
#2810000
b100010101 &
0#
#2815000
b111 -
b110 .
1#
#2820000
b100010110 &
0#
#2825000
b1000 -
b111 .
1#
#2830000
b100010111 &
0#
#2835000
b1001 -
b1000 .
1#
#2840000
b100011000 &
0#
#2845000
b1010 -
b1001 .
1#
#2850000
b100011001 &
0#
#2855000
b1011 -
b1010 .
1#
#2860000
b100011010 &
0#
#2865000
b1100 -
b1011 .
1#
#2870000
b100011011 &
0#
#2875000
b1101 -
b1100 .
1#
#2880000
b100011100 &
0#
#2885000
b1110 -
b1101 .
1#
#2890000
b100011101 &
0#
#2895000
b1111 -
b1110 .
1#
#2900000
b100011110 &
0#
#2905000
b0 -
1,
b1111 .
1#
#2910000
b100011111 &
0#
#2915000
b1 -
1!
0,
b0 .
1#
#2920000
b100100000 &
0#
#2925000
b10 -
0!
b1 .
b10010 "
b10010 '
b10010 (
b10010 *
1#
#2930000
b100100001 &
0#
#2935000
b11 -
b10 .
1#
#2940000
b100100010 &
0#
#2945000
b100 -
b11 .
1#
#2950000
b100100011 &
0#
#2955000
b101 -
b100 .
1#
#2960000
b100100100 &
0#
#2965000
b110 -
b101 .
1#
#2970000
b100100101 &
0#
#2975000
b111 -
b110 .
1#
#2980000
b100100110 &
0#
#2985000
b1000 -
b111 .
1#
#2990000
b100100111 &
0#
#2995000
b1001 -
b1000 .
1#
#3000000
b100101000 &
0#
#3005000
b1010 -
b1001 .
1#
#3010000
b100101001 &
0#
#3015000
b1011 -
b1010 .
1#
#3020000
b100101010 &
0#
#3025000
b1100 -
b1011 .
1#
#3030000
b100101011 &
0#
#3035000
b1101 -
b1100 .
1#
#3040000
b100101100 &
0#
#3045000
b1110 -
b1101 .
1#
#3050000
b100101101 &
0#
#3055000
b1111 -
b1110 .
1#
#3060000
b100101110 &
0#
#3065000
b0 -
1,
b1111 .
1#
#3070000
b100101111 &
0#
#3075000
b1 -
1!
0,
b0 .
1#
#3080000
b100110000 &
0#
#3085000
b10 -
0!
b1 .
b10011 "
b10011 '
b10011 (
b10011 *
1#
#3090000
b100110001 &
0#
#3095000
b11 -
b10 .
1#
#3100000
b100110010 &
0#
#3105000
b100 -
b11 .
1#
#3110000
b100110011 &
0#
#3115000
b101 -
b100 .
1#
#3120000
b100110100 &
0#
#3125000
b110 -
b101 .
1#
#3130000
b100110101 &
0#
#3135000
b111 -
b110 .
1#
#3140000
b100110110 &
0#
#3145000
b1000 -
b111 .
1#
#3150000
b100110111 &
0#
#3155000
b1001 -
b1000 .
1#
#3160000
b100111000 &
0#
#3165000
b1010 -
b1001 .
1#
#3170000
b100111001 &
0#
#3175000
b1011 -
b1010 .
1#
#3180000
b100111010 &
0#
#3185000
b1100 -
b1011 .
1#
#3190000
b100111011 &
0#
#3195000
b1101 -
b1100 .
1#
#3200000
b100111100 &
0#
#3205000
b1110 -
b1101 .
1#
#3210000
b100111101 &
0#
#3215000
b1111 -
b1110 .
1#
#3220000
b100111110 &
0#
#3225000
b0 -
1,
b1111 .
1#
#3230000
b100111111 &
0#
#3235000
b1 -
1!
0,
b0 .
1#
#3240000
b101000000 &
0#
#3245000
b10 -
0!
b1 .
b10100 "
b10100 '
b10100 (
b10100 *
1#
#3250000
b101000001 &
0#
#3255000
b11 -
b10 .
1#
#3260000
b101000010 &
0#
#3265000
b100 -
b11 .
1#
#3270000
b101000011 &
0#
#3275000
b101 -
b100 .
1#
#3280000
b101000100 &
0#
#3285000
b110 -
b101 .
1#
#3290000
b101000101 &
0#
#3295000
b111 -
b110 .
1#
#3300000
b101000110 &
0#
#3305000
b1000 -
b111 .
1#
#3310000
b101000111 &
0#
#3315000
b1001 -
b1000 .
1#
#3320000
b101001000 &
0#
#3325000
b1010 -
b1001 .
1#
#3330000
b101001001 &
0#
#3335000
b1011 -
b1010 .
1#
#3340000
b101001010 &
0#
#3345000
b1100 -
b1011 .
1#
#3350000
b101001011 &
0#
#3355000
b1101 -
b1100 .
1#
#3360000
b101001100 &
0#
#3365000
b1110 -
b1101 .
1#
#3370000
b101001101 &
0#
#3375000
b1111 -
b1110 .
1#
#3380000
b101001110 &
0#
#3385000
b0 -
1,
b1111 .
1#
#3390000
b101001111 &
0#
#3395000
b1 -
1!
0,
b0 .
1#
#3400000
b101010000 &
0#
#3405000
b10 -
0!
b1 .
b10101 "
b10101 '
b10101 (
b10101 *
1#
#3410000
b101010001 &
0#
#3415000
b11 -
b10 .
1#
#3420000
b101010010 &
0#
#3425000
b100 -
b11 .
1#
#3430000
b101010011 &
0#
#3435000
b101 -
b100 .
1#
#3440000
b101010100 &
0#
#3445000
b110 -
b101 .
1#
#3450000
b101010101 &
0#
#3455000
b111 -
b110 .
1#
#3460000
b101010110 &
0#
#3465000
b1000 -
b111 .
1#
#3470000
b101010111 &
0#
#3475000
b1001 -
b1000 .
1#
#3480000
b101011000 &
0#
#3485000
b1010 -
b1001 .
1#
#3490000
b101011001 &
0#
#3495000
b1011 -
b1010 .
1#
#3500000
b101011010 &
0#
#3505000
b1100 -
b1011 .
1#
#3510000
b101011011 &
0#
#3515000
b1101 -
b1100 .
1#
#3520000
b101011100 &
0#
#3525000
b1110 -
b1101 .
1#
#3530000
b101011101 &
0#
#3535000
b1111 -
b1110 .
1#
#3540000
b101011110 &
0#
#3545000
b0 -
1,
b1111 .
1#
#3550000
b101011111 &
0#
#3555000
b1 -
1!
0,
b0 .
1#
#3560000
b101100000 &
0#
#3565000
b10 -
0!
b1 .
b10110 "
b10110 '
b10110 (
b10110 *
1#
#3570000
b101100001 &
0#
#3575000
b11 -
b10 .
1#
#3580000
b101100010 &
0#
#3585000
b100 -
b11 .
1#
#3590000
b101100011 &
0#
#3595000
b101 -
b100 .
1#
#3600000
b101100100 &
0#
#3605000
b110 -
b101 .
1#
#3610000
b101100101 &
0#
#3615000
b111 -
b110 .
1#
#3620000
b101100110 &
0#
#3625000
b1000 -
b111 .
1#
#3630000
b101100111 &
0#
#3635000
b1001 -
b1000 .
1#
#3640000
b101101000 &
0#
#3645000
b1010 -
b1001 .
1#
#3650000
b101101001 &
0#
#3655000
b1011 -
b1010 .
1#
#3660000
b101101010 &
0#
#3665000
b1100 -
b1011 .
1#
#3670000
b101101011 &
0#
#3675000
b1101 -
b1100 .
1#
#3680000
b101101100 &
0#
#3685000
b1110 -
b1101 .
1#
#3690000
b101101101 &
0#
#3695000
b1111 -
b1110 .
1#
#3700000
b101101110 &
0#
#3705000
b0 -
1,
b1111 .
1#
#3710000
b101101111 &
0#
#3715000
b1 -
1!
0,
b0 .
1#
#3720000
b101110000 &
0#
#3725000
b10 -
0!
b1 .
b10111 "
b10111 '
b10111 (
b10111 *
1#
#3730000
b101110001 &
0#
#3735000
b11 -
b10 .
1#
#3740000
b101110010 &
0#
#3745000
b100 -
b11 .
1#
#3750000
b101110011 &
0#
#3755000
b101 -
b100 .
1#
