experiments/eda-lab-iverilog-vcd-wave/counter.v
// counter.v —— 两层层级的小设计：顶层 counter_top 里挂一个 baud_gen 子模块
// 故意多放内部信号，方便演示 $dumpvars 层级/范围控制对 VCD 大小的影响。

module baud_gen (
    input  wire        clk,
    input  wire        rst_n,
    input  wire [7:0]  div,
    output reg         tick
);
    reg [7:0] cnt;
    // 内部中间信号：全量 dump 时它们也会进 VCD
    wire [7:0] cnt_next = (cnt >= div) ? 8'd0 : cnt + 8'd1;
    wire       hit      = (cnt >= div);

    always @(posedge clk or negedge rst_n) begin
        if (!rst_n) begin
            cnt  <= 8'd0;
            tick <= 1'b0;
        end else begin
            cnt  <= cnt_next;
            tick <= hit;
        end
    end
endmodule

module counter_top (
    input  wire        clk,
    input  wire        rst_n,
    input  wire        en,
    output wire [7:0]  count,
    output wire        tick
);
    reg [7:0] cnt_r;
    // 内部统计信号：仿真过程可见、平时看波形很少关心
    reg [15:0] tick_total;
    reg [7:0]  div_cfg;

    baud_gen u_baud (
        .clk   (clk),
        .rst_n (rst_n),
        .div   (div_cfg),
        .tick  (tick)
    );

    assign count = cnt_r;

    always @(posedge clk or negedge rst_n) begin
        if (!rst_n) begin
            cnt_r      <= 8'd0;
            tick_total <= 16'd0;
            div_cfg    <= 8'd15;
        end else begin
            if (tick) begin
                tick_total <= tick_total + 16'd1;
                if (en) cnt_r <= cnt_r + 8'd1;
            end
        end
    end
endmodule

experiments/eda-lab-iverilog-vcd-wave/tb_slim.v
// tb_slim.v —— 瘦身 dump：同一设计、同一激励，只 dump TB 顶层 1 层信号，
// 并用 $dumpon/$dumpoff 跳过复位后的前 1000 拍预热段。
`timescale 1ns/1ps
module tb_slim;
    reg        clk = 0;
    reg        rst_n = 0;
    reg        en = 0;
    wire [7:0] count;
    wire       tick;

    counter_top dut (
        .clk   (clk),
        .rst_n (rst_n),
        .en    (en),
        .count (count),
        .tick  (tick)
    );

    always #5 clk = ~clk;

    integer i;
    initial begin
        $dumpfile("slim.vcd");
        // depth=1：只记录 tb_slim 这一层的信号（clk/rst_n/en/count/tick），
        // dut 内部和 u_baud 内部全部不进 VCD
        $dumpvars(1, tb_slim);
        repeat (4) @(negedge clk);
        rst_n = 1;
        en = 1;
        // 前 1000 拍是预热，不看 → 暂停 dump
        $dumpoff;
        for (i = 0; i < 1000; i = i + 1) @(negedge clk);
        $dumpon;
        for (i = 0; i < 19000; i = i + 1) @(negedge clk);
        $dumpflush;
        $display("SLIM DONE count=%0d", count);
        $finish;
    end
endmodule

experiments/eda-lab-iverilog-vcd-wave/slim.vcd
$date
	Wed Oct  7 14:58:20 2026
$end
$version
	Icarus Verilog
$end
$timescale
	1ps
$end
$scope module tb_slim $end
$var wire 1 ! tick $end
$var wire 8 " count [7:0] $end
$var reg 1 # clk $end
$var reg 1 $ en $end
$var reg 1 % rst_n $end
$var integer 32 & i [31:0] $end
$upscope $end
$enddefinitions $end
$comment Show the parameter values. $end
$dumpall
$end
#0
$dumpvars
bx &
0%
0$
0#
bx "
x!
$end
#5000
0!
b0 "
1#
#10000
0#
#15000
1#
#20000
0#
#25000
1#
#30000
0#
#35000
1#
#40000
$dumpoff
bx &
x%
x$
x#
bx "
x!
$end
1$
1%
0#
#10040000
$dumpon
b1111101000 &
1%
1$
0#
b111110 "
0!
$end
b0 &
#10045000
1#
#10050000
b1 &
0#
#10055000
1#
#10060000
b10 &
0#
#10065000
1#
#10070000
b11 &
0#
#10075000
1#
#10080000
b100 &
0#
#10085000
1#
#10090000
b101 &
0#
#10095000
1#
#10100000
b110 &
0#
#10105000
1#
#10110000
b111 &
0#
#10115000
1!
1#
#10120000
b1000 &
0#
#10125000
0!
b111111 "
1#
#10130000
b1001 &
0#
#10135000
1#
#10140000
b1010 &
0#
#10145000
1#
#10150000
b1011 &
0#
#10155000
1#
#10160000
b1100 &
0#
#10165000
1#
#10170000
b1101 &
0#
#10175000
1#
#10180000
b1110 &
0#
#10185000
1#
#10190000
b1111 &
0#
#10195000
1#
#10200000
b10000 &
0#
#10205000
1#
#10210000
b10001 &
0#
#10215000
1#
#10220000
b10010 &
0#
#10225000
1#
#10230000
b10011 &
0#
#10235000
1#
#10240000
b10100 &
0#
#10245000
1#
#10250000
b10101 &
0#
#10255000
1#
#10260000
b10110 &
0#
#10265000
1#
#10270000
b10111 &
0#
#10275000
1!
1#
#10280000
b11000 &
0#
#10285000
0!
b1000000 "
1#
#10290000
b11001 &
0#
#10295000
1#
#10300000
b11010 &
0#
#10305000
1#
#10310000
b11011 &
0#
#10315000
1#
#10320000
b11100 &
0#
#10325000
1#
#10330000
b11101 &
0#
#10335000
1#
#10340000
b11110 &
0#
#10345000
1#
#10350000
b11111 &
0#
#10355000
1#
#10360000
b100000 &
0#
#10365000
1#
#10370000
b100001 &
0#
#10375000
1#
#10380000
b100010 &
0#
#10385000
1#
#10390000
b100011 &
0#
#10395000
1#
#10400000
b100100 &
0#
#10405000
1#
#10410000
b100101 &
0#
#10415000
1#
#10420000
b100110 &
0#
#10425000
1#
#10430000
b100111 &
0#
#10435000
1!
1#
#10440000
b101000 &
0#
#10445000
0!
b1000001 "
1#
#10450000
b101001 &
0#
#10455000
1#
#10460000
b101010 &
0#
#10465000
1#
#10470000
b101011 &
0#
#10475000
1#
#10480000
b101100 &
0#
#10485000
1#
#10490000
b101101 &
0#
#10495000
1#
#10500000
b101110 &
0#
#10505000
1#
#10510000
b101111 &
0#
#10515000
1#
#10520000
b110000 &
0#
#10525000
1#
#10530000
b110001 &
0#
#10535000
1#
#10540000
b110010 &
0#
#10545000
1#
#10550000
b110011 &
0#
#10555000
1#
#10560000
b110100 &
0#
#10565000
1#
#10570000
b110101 &
0#
#10575000
1#
#10580000
b110110 &
0#
#10585000
1#
#10590000
b110111 &
0#
#10595000
1!
1#
#10600000
b111000 &
0#
#10605000
0!
b1000010 "
1#
#10610000
b111001 &
0#
#10615000
1#
#10620000
b111010 &
0#
#10625000
1#
#10630000
b111011 &
0#
#10635000
1#
#10640000
b111100 &
0#
#10645000
1#
#10650000
b111101 &
0#
#10655000
1#
#10660000
b111110 &
0#
#10665000
1#
#10670000
b111111 &
0#
#10675000
1#
#10680000
b1000000 &
0#
#10685000
1#
#10690000
b1000001 &
0#
#10695000
1#
#10700000
b1000010 &
0#
#10705000
1#
#10710000
b1000011 &
0#
#10715000
1#
#10720000
b1000100 &
0#
#10725000
1#
#10730000
b1000101 &
0#
#10735000
1#
#10740000
b1000110 &
0#
#10745000
1#
#10750000
b1000111 &
0#
#10755000
1!
1#
#10760000
b1001000 &
0#
#10765000
0!
b1000011 "
1#
#10770000
b1001001 &
0#
#10775000
1#
#10780000
b1001010 &
0#
#10785000
1#
#10790000
b1001011 &
0#
#10795000
1#
#10800000
b1001100 &
0#
#10805000
1#
#10810000
b1001101 &
0#
#10815000
1#
#10820000
b1001110 &
0#
#10825000
1#
#10830000
b1001111 &
0#
#10835000
1#
#10840000
b1010000 &
0#
#10845000
1#
#10850000
b1010001 &
0#
#10855000
1#
#10860000
b1010010 &
0#
#10865000
1#
#10870000
b1010011 &
0#
#10875000
1#
#10880000
b1010100 &
0#
#10885000
1#
#10890000
b1010101 &
0#
#10895000
1#
#10900000
b1010110 &
0#
#10905000
1#
#10910000
b1010111 &
0#
#10915000
1!
1#
#10920000
b1011000 &
0#
#10925000
0!
b1000100 "
1#
#10930000
b1011001 &
0#
#10935000
1#
#10940000
b1011010 &
0#
#10945000
1#
#10950000
b1011011 &
0#
#10955000
1#
#10960000
b1011100 &
0#
#10965000
1#
#10970000
b1011101 &
0#
#10975000
1#
#10980000
b1011110 &
0#
#10985000
1#
#10990000
b1011111 &
0#
#10995000
1#
#11000000
b1100000 &
0#
#11005000
1#
#11010000
b1100001 &
0#
#11015000
1#
#11020000
b1100010 &
0#
#11025000
1#
#11030000
b1100011 &
0#
#11035000
1#
#11040000
b1100100 &
0#
#11045000
1#
#11050000
b1100101 &
0#
#11055000
1#
#11060000
b1100110 &
0#
#11065000
1#
#11070000
b1100111 &
0#
#11075000
1!
1#
#11080000
b1101000 &
0#
#11085000
0!
b1000101 "
1#
#11090000
b1101001 &
0#
#11095000
1#
#11100000
b1101010 &
0#
#11105000
1#
#11110000
b1101011 &
0#
#11115000
1#
#11120000
b1101100 &
0#
#11125000
1#
#11130000
b1101101 &
0#
#11135000
1#
#11140000
b1101110 &
0#
#11145000
1#
#11150000
b1101111 &
0#
#11155000
1#
#11160000
b1110000 &
0#
#11165000
1#
#11170000
b1110001 &
0#
#11175000
1#
#11180000
b1110010 &
0#
#11185000
1#
#11190000
b1110011 &
0#
#11195000
1#
#11200000
b1110100 &
0#
#11205000
1#
#11210000
b1110101 &
0#
#11215000
1#
#11220000
b1110110 &
0#
#11225000
1#
#11230000
b1110111 &
0#
#11235000
1!
1#
#11240000
b1111000 &
0#
#11245000
0!
b1000110 "
1#
#11250000
b1111001 &
0#
#11255000
1#
#11260000
b1111010 &
0#
#11265000
1#
#11270000
b1111011 &
0#
#11275000
1#
#11280000
b1111100 &
0#
#11285000
1#
#11290000
b1111101 &
0#
#11295000
1#
#11300000
b1111110 &
0#
#11305000
1#
#11310000
b1111111 &
0#
#11315000
1#
#11320000
b10000000 &
0#
#11325000
1#
#11330000
b10000001 &
0#
#11335000
1#
#11340000
b10000010 &
0#
#11345000
1#
#11350000
b10000011 &
0#
#11355000
1#
#11360000
b10000100 &
0#
#11365000
1#
#11370000
b10000101 &
0#
#11375000
1#
#11380000
b10000110 &
0#
#11385000
1#
#11390000
b10000111 &
0#
#11395000
1!
1#
#11400000
b10001000 &
0#
#11405000
0!
b1000111 "
1#
#11410000
b10001001 &
0#
#11415000
1#
#11420000
b10001010 &
0#
#11425000
1#
#11430000
b10001011 &
0#
#11435000
1#
#11440000
b10001100 &
0#
#11445000
1#
#11450000
b10001101 &
0#
#11455000
1#
#11460000
b10001110 &
0#
#11465000
1#
#11470000
b10001111 &
0#
#11475000
1#
#11480000
b10010000 &
0#
#11485000
1#
#11490000
b10010001 &
0#
#11495000
1#
#11500000
b10010010 &
0#
#11505000
1#
#11510000
b10010011 &
0#
#11515000
1#
#11520000
b10010100 &
0#
#11525000
1#
#11530000
b10010101 &
0#
#11535000
1#
#11540000
b10010110 &
0#
#11545000
1#
#11550000
b10010111 &
0#
#11555000
1!
1#
#11560000
b10011000 &
0#
#11565000
0!
b1001000 "
1#
#11570000
b10011001 &
0#
#11575000
1#
#11580000
b10011010 &
0#
#11585000
1#
#11590000
b10011011 &
0#
#11595000
1#
#11600000
b10011100 &
0#
#11605000
1#
#11610000
b10011101 &
0#
#11615000
1#
#11620000
b10011110 &
0#
#11625000
1#
#11630000
b10011111 &
0#
#11635000
1#
#11640000
b10100000 &
0#
#11645000
1#
#11650000
b10100001 &
0#
#11655000
1#
#11660000
b10100010 &
0#
#11665000
1#
#11670000
b10100011 &
0#
#11675000
1#
#11680000
b10100100 &
0#
#11685000
1#
#11690000
b10100101 &
0#
#11695000
1#
#11700000
b10100110 &
0#
#11705000
1#
#11710000
b10100111 &
0#
#11715000
1!
1#
#11720000
b10101000 &
0#
#11725000
0!
b1001001 "
1#
#11730000
b10101001 &
0#
#11735000
1#
#11740000
b10101010 &
0#
#11745000
1#
#11750000
b10101011 &
0#
#11755000
1#
#11760000
b10101100 &
0#
#11765000
1#
#11770000
b10101101 &
0#
#11775000
1#
#11780000
b10101110 &
0#
#11785000
1#
#11790000
b10101111 &
0#
#11795000
1#
#11800000
b10110000 &
0#
#11805000
1#
#11810000
b10110001 &
0#
#11815000
1#
#11820000
b10110010 &
0#
#11825000
1#
#11830000
b10110011 &
0#
#11835000
1#
#11840000
b10110100 &
0#
#11845000
1#
#11850000
b10110101 &
0#
#11855000
1#
#11860000
b10110110 &
0#
#11865000
1#
#11870000
b10110111 &
0#
#11875000
1!
1#
#11880000
b10111000 &
0#
#11885000
0!
b1001010 "
1#
#11890000
b10111001 &
0#
#11895000
1#
#11900000
b10111010 &
0#
#11905000
1#
#11910000
b10111011 &
0#
#11915000
1#
#11920000
b10111100 &
0#
#11925000
1#
#11930000
b10111101 &
0#
#11935000
1#
#11940000
b10111110 &
0#
#11945000
1#
#11950000
b10111111 &
0#
#11955000
1#
#11960000
b11000000 &
0#
#11965000
1#
#11970000
b11000001 &
0#
#11975000
1#
#11980000
b11000010 &
0#
#11985000
1#
#11990000
b11000011 &
0#
#11995000
1#
#12000000
b11000100 &
0#
#12005000
1#
#12010000
b11000101 &
0#
#12015000
1#
#12020000
b11000110 &
0#
#12025000
1#
#12030000
b11000111 &
0#
#12035000
1!
1#
#12040000
b11001000 &
0#
#12045000
0!
b1001011 "
1#
#12050000
b11001001 &
0#
#12055000
1#
#12060000
b11001010 &
0#
#12065000
1#
#12070000
b11001011 &
0#
#12075000
1#
#12080000
b11001100 &
0#
#12085000
1#
#12090000
b11001101 &
0#
#12095000
1#
#12100000
b11001110 &
0#
#12105000
1#
#12110000
b11001111 &
0#
#12115000
1#
#12120000
b11010000 &
0#
#12125000
1#
#12130000
b11010001 &
0#
#12135000
1#
#12140000
b11010010 &
0#
#12145000
1#
#12150000
b11010011 &
0#
#12155000
1#
#12160000
b11010100 &
0#
#12165000
1#
#12170000
b11010101 &
0#
#12175000
1#
#12180000
b11010110 &
0#
#12185000
1#
#12190000
b11010111 &
0#
#12195000
1!
1#
#12200000
b11011000 &
0#
#12205000
0!
b1001100 "
1#
#12210000
b11011001 &
0#
#12215000
1#
#12220000
b11011010 &
0#
#12225000
1#
#12230000
b11011011 &
0#
#12235000
1#
#12240000
b11011100 &
0#
#12245000
1#
#12250000
b11011101 &
0#
#12255000
1#
#12260000
b11011110 &
0#
#12265000
1#
#12270000
b11011111 &
0#
#12275000
1#
#12280000
b11100000 &
0#
#12285000
1#
#12290000
b11100001 &
0#
#12295000
1#
#12300000
b11100010 &
0#
#12305000
1#
#12310000
b11100011 &
0#
#12315000
1#
#12320000
b11100100 &
0#
#12325000
1#
#12330000
b11100101 &
0#
#12335000
1#
#12340000
b11100110 &
0#
#12345000
1#
#12350000
b11100111 &
0#
#12355000
1!
1#
#12360000
b11101000 &
0#
#12365000
0!
b1001101 "
1#
#12370000
b11101001 &
0#
#12375000
1#
#12380000
b11101010 &
0#
#12385000
1#
#12390000
b11101011 &
0#
#12395000
1#
#12400000
b11101100 &
0#
#12405000
1#
#12410000
b11101101 &
0#
#12415000
1#
#12420000
b11101110 &
0#
#12425000
1#
#12430000
b11101111 &
0#
#12435000
1#
#12440000
b11110000 &
0#
#12445000
1#
#12450000
b11110001 &
0#
#12455000
1#
#12460000
b11110010 &
0#
#12465000
1#
#12470000
b11110011 &
0#
#12475000
1#
#12480000
b11110100 &
0#
#12485000
1#
#12490000
b11110101 &
0#
#12495000
1#
#12500000
b11110110 &
0#
#12505000
1#
#12510000
b11110111 &
0#
#12515000
1!
1#
#12520000
b11111000 &
0#
#12525000
0!
b1001110 "
1#
#12530000
b11111001 &
0#
#12535000
1#
#12540000
b11111010 &
0#
#12545000
1#
#12550000
b11111011 &
0#
#12555000
1#
#12560000
b11111100 &
0#
#12565000
1#
#12570000
b11111101 &
0#
#12575000
1#
#12580000
b11111110 &
0#
#12585000
1#
#12590000
b11111111 &
0#
#12595000
1#
#12600000
b100000000 &
0#
#12605000
1#
#12610000
b100000001 &
0#
#12615000
1#
#12620000
b100000010 &
0#
#12625000
1#
#12630000
b100000011 &
0#
#12635000
1#
#12640000
b100000100 &
0#
#12645000
1#
#12650000
b100000101 &
0#
#12655000
1#
#12660000
b100000110 &
0#
#12665000
1#
#12670000
b100000111 &
0#
#12675000
1!
1#
#12680000
b100001000 &
0#
#12685000
0!
b1001111 "
1#
#12690000
b100001001 &
0#
#12695000
1#
#12700000
b100001010 &
0#
#12705000
1#
#12710000
b100001011 &
0#
#12715000
1#
#12720000
b100001100 &
0#
#12725000
1#
#12730000
b100001101 &
0#
#12735000
1#
#12740000
b100001110 &
0#
#12745000
1#
#12750000
b100001111 &
0#
#12755000
1#
#12760000
b100010000 &
0#
#12765000
1#
#12770000
b100010001 &
0#
#12775000
1#
#12780000
b100010010 &
0#
#12785000
1#
#12790000
b100010011 &
0#
#12795000
1#
#12800000
b100010100 &
0#
#12805000
1#
#12810000
b100010101 &
0#
#12815000
1#
#12820000
b100010110 &
0#
#12825000
1#
#12830000
b100010111 &
0#
#12835000
1!
1#
#12840000
b100011000 &
0#
#12845000
0!
b1010000 "
1#
#12850000
b100011001 &
0#
#12855000
1#
#12860000
b100011010 &
0#
#12865000
1#
#12870000
b100011011 &
0#
#12875000
1#
#12880000
b100011100 &
0#
#12885000
1#
#12890000
b100011101 &
0#
#12895000
1#
#12900000
b100011110 &
0#
#12905000
1#
#12910000
b100011111 &
0#
#12915000
1#
#12920000
b100100000 &
0#
#12925000
1#
#12930000
b100100001 &
0#
#12935000
1#
#12940000
b100100010 &
0#
#12945000
1#
#12950000
b100100011 &
0#
#12955000
1#
#12960000
b100100100 &
0#
#12965000
1#
#12970000
b100100101 &
0#
#12975000
1#
#12980000
b100100110 &
0#
#12985000
1#
#12990000
b100100111 &
0#
#12995000
1!
1#
#13000000
b100101000 &
0#
#13005000
0!
b1010001 "
1#
#13010000
b100101001 &
0#
#13015000
1#
#13020000
b100101010 &
0#
#13025000
1#
#13030000
b100101011 &
0#
#13035000
1#
#13040000
b100101100 &
0#
#13045000
1#
#13050000
b100101101 &
0#
#13055000
1#
#13060000
b100101110 &
0#
#13065000
1#
#13070000
b100101111 &
0#
#13075000
1#
#13080000
b100110000 &
0#
#13085000
1#
#13090000
b100110001 &
0#
#13095000
1#
#13100000
b100110010 &
0#
#13105000
1#
#13110000
b100110011 &
0#
#13115000
1#
#13120000
b100110100 &
0#
#13125000
1#
#13130000
b100110101 &
0#
#13135000
1#
#13140000
b100110110 &
0#
#13145000
1#
#13150000
b100110111 &
0#
#13155000
1!
1#
#13160000
b100111000 &
0#
#13165000
0!
b1010010 "
1#
#13170000
b100111001 &
0#
#13175000
1#
#13180000
b100111010 &
0#
#13185000
1#
#13190000
b100111011 &
0#
#13195000
1#
#13200000
b100111100 &
0#
#13205000
1#
#13210000
b100111101 &
0#
#13215000
1#
#13220000
b100111110 &
0#
#13225000
1#
#13230000
b100111111 &
0#
#13235000
1#
#13240000
b101000000 &
0#
#13245000
1#
#13250000
b101000001 &
0#
#13255000
1#
#13260000
b101000010 &
0#
#13265000
1#
#13270000
b101000011 &
0#
#13275000
1#
#13280000
b101000100 &
0#
#13285000
1#
#13290000
b101000101 &
0#
#13295000
1#
#13300000
b101000110 &
0#
#13305000
1#
#13310000
b101000111 &
0#
#13315000
1!
1#
#13320000
b101001000 &
0#
#13325000
0!
b1010011 "
1#
#13330000
b101001001 &
0#
#13335000
1#
#13340000
b101001010 &
0#
#13345000
1#
#13350000
b101001011 &
0#
#13355000
1#
#13360000
b101001100 &
0#
#13365000
1#
#13370000
b101001101 &
0#
#13375000
1#
#13380000
b101001110 &
0#
#13385000
1#
#13390000
b101001111 &
0#
#13395000
1#
#13400000
b101010000 &
0#
#13405000
1#
#13410000
b101010001 &
0#
#13415000
1#
#13420000
b101010010 &
0#
#13425000
1#
#13430000
b101010011 &
0#
#13435000
1#
#13440000
b101010100 &
0#
#13445000
1#
#13450000
b101010101 &
0#
#13455000
1#
#13460000
b101010110 &
0#
#13465000
1#
#13470000
b101010111 &
0#
#13475000
1!
1#
#13480000
b101011000 &
0#
#13485000
0!
b1010100 "
1#
#13490000
b101011001 &
0#
#13495000
1#
#13500000
b101011010 &
0#
#13505000
1#
#13510000
b101011011 &
0#
#13515000
1#
#13520000
b101011100 &
0#
#13525000
1#
#13530000
b101011101 &
0#
#13535000
1#
#13540000
b101011110 &
0#
#13545000
1#
#13550000
b101011111 &
0#
#13555000
1#
#13560000
b101100000 &
0#
#13565000
1#
#13570000
b101100001 &
0#
#13575000
1#
#13580000
b101100010 &
0#
#13585000
1#
#13590000
b101100011 &
0#
#13595000
1#
#13600000
b101100100 &
0#
#13605000
1#
#13610000
b101100101 &
0#
#13615000
1#
#13620000
b101100110 &
0#
#13625000
1#
#13630000
b101100111 &
0#
#13635000
1!
1#
#13640000
b101101000 &
0#
#13645000
0!
b1010101 "
1#
#13650000
b101101001 &
0#
#13655000
1#
#13660000
b101101010 &
0#
#13665000
1#
#13670000
b101101011 &
0#
#13675000
1#
#13680000
b101101100 &
0#
#13685000
1#
#13690000
b101101101 &
0#
#13695000
1#
#13700000
b101101110 &
0#
#13705000
1#
#13710000
b101101111 &
0#
#13715000
1#
#13720000
b101110000 &
0#
#13725000
1#
#13730000
b101110001 &
0#
#13735000
1#
#13740000
b101110010 &
0#
#13745000
1#
#13750000
b101110011 &
0#
#13755000
1#
#13760000
b101110100 &
0#
#13765000
1#
#13770000
b101110101 &
0#
#13775000
1#
#13780000
b101110110 &
0#
#13785000
1#
#13790000
b101110111 &
0#
#13795000
1!
1#
#13800000
b101111000 &
0#
#13805000
0!
b1010110 "
1#
#13810000
b101111001 &
0#
#13815000
1#
#13820000
b101111010 &
0#
#13825000
1#
#13830000
b101111011 &
0#
#13835000
1#
#13840000
b101111100 &
0#
#13845000
1#
#13850000
b101111101 &
0#
#13855000
1#
#13860000
b101111110 &
0#
#13865000
1#
#13870000
b101111111 &
0#
#13875000
1#
#13880000
b110000000 &
0#
#13885000
1#
#13890000
b110000001 &
0#
#13895000
1#
#13900000
b110000010 &
0#
#13905000
1#
#13910000
b110000011 &
0#
#13915000
1#
#13920000
b110000100 &
0#
#13925000
1#
#13930000
b110000101 &
0#
#13935000
1#
#13940000
b110000110 &
0#
#13945000
1#
#13950000
b110000111 &
0#
#13955000
1!
1#
#13960000
b110001000 &
0#
#13965000
0!
b1010111 "
1#
#13970000
b110001001 &
0#
#13975000
1#
#13980000
b110001010 &
0#
#13985000
1#
#13990000
b110001011 &
0#
#13995000
1#
#14000000
b110001100 &
0#
#14005000
1#
#14010000
b110001101 &
0#
#14015000
1#
#14020000
b110001110 &
0#
#14025000
1#
#14030000
b110001111 &
0#
#14035000
1#
#14040000
b110010000 &
0#
#14045000
1#
#14050000
b110010001 &
0#
#14055000
1#
#14060000
b110010010 &
0#
#14065000
1#
#14070000
b110010011 &
0#
#14075000
1#
#14080000
b110010100 &
0#
#14085000
1#
#14090000
b110010101 &
0#
#14095000
1#
#14100000
b110010110 &
0#
#14105000
1#
#14110000
b110010111 &
0#
#14115000
1!
1#
#14120000
b110011000 &
0#
#14125000
0!
b1011000 "
1#
#14130000
b110011001 &
0#
#14135000
1#
#14140000
b110011010 &
0#
#14145000
1#
#14150000
b110011011 &
0#
#14155000
1#
#14160000
b110011100 &
0#
#14165000
1#
#14170000
b110011101 &
0#
#14175000
1#
#14180000
b110011110 &
0#
#14185000
1#
#14190000
b110011111 &
0#
#14195000
1#
#14200000
b110100000 &
0#
#14205000
1#
#14210000
b110100001 &
0#
#14215000
1#
#14220000
b110100010 &
0#
#14225000
1#
#14230000
b110100011 &
0#
#14235000
1#
#14240000
b110100100 &
0#
#14245000
1#
#14250000
b110100101 &
0#
#14255000
1#
#14260000
b110100110 &
0#
#14265000
1#
#14270000
b110100111 &
0#
#14275000
1!
1#
#14280000
b110101000 &
0#
#14285000
0!
b1011001 "
1#
#14290000
b110101001 &
0#
#14295000
1#
#14300000
b110101010 &
0#
#14305000
1#
#14310000
b110101011 &
0#
#14315000
1#
#14320000
b110101100 &
0#
#14325000
1#
#14330000
b110101101 &
0#
#14335000
1#
#14340000
b110101110 &
0#
#14345000
1#
#14350000
b110101111 &
0#
#14355000
1#
#14360000
b110110000 &
0#
#14365000
1#
#14370000
b110110001 &
0#
#14375000
1#
#14380000
b110110010 &
0#
#14385000
1#
#14390000
b110110011 &
0#
#14395000
1#
#14400000
b110110100 &
0#
#14405000
1#
#14410000
b110110101 &
0#
#14415000
1#
#14420000
b110110110 &
0#
#14425000
1#
#14430000
b110110111 &
0#
#14435000
1!
1#
#14440000
b110111000 &
0#
#14445000
0!
b1011010 "
1#
#14450000
b110111001 &
0#
#14455000
1#
#14460000
b110111010 &
0#
#14465000
1#
#14470000
b110111011 &
0#
#14475000
1#
#14480000
b110111100 &
0#
#14485000
1#
#14490000
b110111101 &
0#
#14495000
1#
#14500000
b110111110 &
0#
#14505000
1#
#14510000
b110111111 &
0#
#14515000
1#
#14520000
b111000000 &
0#
#14525000
1#
#14530000
b111000001 &
0#
#14535000
1#
#14540000
b111000010 &
0#
#14545000
1#
#14550000
b111000011 &
0#
#14555000
1#
#14560000
b111000100 &
0#
#14565000
1#
#14570000
b111000101 &
0#
#14575000
1#
#14580000
b111000110 &
0#
#14585000
1#
#14590000
b111000111 &
0#
#14595000
1!
1#
#14600000
b111001000 &
0#
#14605000
0!
b1011011 "
1#
#14610000
b111001001 &
0#
#14615000
1#
#14620000
b111001010 &
0#
#14625000
1#
#14630000
b111001011 &
0#
#14635000
1#
#14640000
b111001100 &
0#
#14645000
1#
#14650000
b111001101 &
0#
#14655000
1#
#14660000
b111001110 &
0#
#14665000
1#
#14670000
b111001111 &
0#
#14675000
1#
#14680000
b111010000 &
0#
#14685000
1#
#14690000
b111010001 &
0#
#14695000
1#
#14700000
b111010010 &
0#
#14705000
1#
#14710000
b111010011 &
0#
#14715000
1#
#14720000
b111010100 &
0#
#14725000
1#
#14730000
b111010101 &
0#
#14735000
1#
#14740000
b111010110 &
0#
#14745000
1#
#14750000
b111010111 &
0#
#14755000
1!
1#
#14760000
b111011000 &
0#
#14765000
0!
b1011100 "
1#
#14770000
b111011001 &
0#
#14775000
1#
#14780000
b111011010 &
0#
#14785000
1#
#14790000
b111011011 &
0#
#14795000
1#
#14800000
b111011100 &
0#
#14805000
1#
#14810000
b111011101 &
0#
#14815000
1#
#14820000
b111011110 &
0#
#14825000
1#
#14830000
b111011111 &
0#
#14835000
1#
#14840000
b111100000 &
0#
#14845000
1#
#14850000
b111100001 &
0#
#14855000
1#
#14860000
b111100010 &
0#
#14865000
1#
#14870000
b111100011 &
0#
#14875000
1#
#14880000
b111100100 &
0#
#14885000
1#
#14890000
b111100101 &
0#
#14895000
1#
#14900000
b111100110 &
0#
#14905000
1#
#14910000
b111100111 &
0#
#14915000
1!
1#
#14920000
b111101000 &
0#
#14925000
0!
b1011101 "
1#
#14930000
b111101001 &
0#
#14935000
1#
#14940000
b111101010 &
0#
#14945000
1#
#14950000
b111101011 &
0#
#14955000
1#
#14960000
b111101100 &
0#
#14965000
1#
#14970000
b111101101 &
0#
#14975000
1#
#14980000
b111101110 &
0#
#14985000
1#
#14990000
b111101111 &
0#
#14995000
1#
#15000000
b111110000 &
0#
#15005000
1#
#15010000
b111110001 &
0#
#15015000
1#
#15020000
b111110010 &
0#
#15025000
1#
#15030000
b111110011 &
0#
#15035000
1#
#15040000
b111110100 &
0#
#15045000
1#
#15050000
b111110101 &
0#
#15055000
1#
#15060000
b111110110 &
0#
#15065000
1#
#15070000
b111110111 &
0#
#15075000
1!
1#
#15080000
b111111000 &
0#
#15085000
0!
b1011110 "
1#
#15090000
b111111001 &
0#
#15095000
1#
#15100000
b111111010 &
0#
#15105000
1#
#15110000
b111111011 &
0#
#15115000
1#
#15120000
b111111100 &
0#
#15125000
1#
#15130000
b111111101 &
0#
#15135000
1#
#15140000
b111111110 &
0#
#15145000
1#
#15150000
b111111111 &
0#
#15155000
1#
#15160000
b1000000000 &
0#
#15165000
1#
#15170000
b1000000001 &
0#
#15175000
1#
#15180000
b1000000010 &
0#
#15185000
1#
#15190000
b1000000011 &
0#
#15195000
1#
#15200000
b1000000100 &
0#
#15205000
1#
#15210000
b1000000101 &
0#
#15215000
1#
#15220000
b1000000110 &
0#
#15225000
1#
#15230000
b1000000111 &
0#
#15235000
1!
1#
#15240000
b1000001000 &
0#
#15245000
0!
b1011111 "
1#
#15250000
b1000001001 &
0#
#15255000
1#
#15260000
b1000001010 &
0#
#15265000
1#
#15270000
b1000001011 &
0#
#15275000
1#
#15280000
b1000001100 &
0#
#15285000
1#
#15290000
b1000001101 &
0#
#15295000
1#
#15300000
b1000001110 &
0#
#15305000
1#
#15310000
b1000001111 &
0#
#15315000
1#
#15320000
b1000010000 &
0#
#15325000
1#
#15330000
b1000010001 &
0#
#15335000
1#
#15340000
b1000010010 &
0#
#15345000
1#
#15350000
b1000010011 &
0#
#15355000
1#
#15360000
b1000010100 &
0#
#15365000
1#
#15370000
b1000010101 &
0#
#15375000
1#
#15380000
b1000010110 &
0#
#15385000
1#
#15390000
b1000010111 &
0#
#15395000
1!
1#
#15400000
b1000011000 &
0#
#15405000
0!
b1100000 "
1#
#15410000
b1000011001 &
0#
#15415000
1#
#15420000
b1000011010 &
0#
#15425000
1#
#15430000
b1000011011 &
0#
#15435000
1#
#15440000
b1000011100 &
0#
#15445000
1#
#15450000
b1000011101 &
0#
#15455000
1#
#15460000
b1000011110 &
0#
#15465000
1#
#15470000
b1000011111 &
0#
#15475000
1#
#15480000
b1000100000 &
0#
#15485000
1#
#15490000
b1000100001 &
0#
#15495000
1#
#15500000
b1000100010 &
0#
#15505000
1#
#15510000
b1000100011 &
0#
#15515000
1#
#15520000
b1000100100 &
0#
#15525000
1#
#15530000
b1000100101 &
0#
#15535000
1#
#15540000
b1000100110 &
0#
#15545000
1#
#15550000
b1000100111 &
0#
#15555000
1!
1#
#15560000
b1000101000 &
0#
#15565000
0!
b1100001 "
1#
#15570000
b1000101001 &
0#
#15575000
1#
#15580000
b1000101010 &
0#
#15585000
1#
#15590000
b1000101011 &
0#
#15595000
1#
#15600000
b1000101100 &
0#
#15605000
1#
#15610000
b1000101101 &
0#
#15615000
1#
#15620000
b1000101110 &
0#
#15625000
1#
#15630000
b1000101111 &
0#
#15635000
1#
#15640000
b1000110000 &
0#
#15645000
1#
