experiments/eda-lab-iverilog-first-sim/counter.v
// counter.v —— 4 位计数器（iverilog 仿真入门实验被测设计）
// 功能：同步复位、使能计数，溢出自然回绕。
module counter (
    input  wire       clk,    // 时钟
    input  wire       rst_n,  // 低有效同步复位
    input  wire       en,     // 计数使能
    output reg  [3:0] count   // 4 位计数值
);

    always @(posedge clk) begin
        if (!rst_n)
            count <= 4'd0;
        else if (en)
            count <= count + 4'd1;
        // en 为 0 时保持
    end

endmodule

experiments/eda-lab-iverilog-first-sim/counter_tb.v
// counter_tb.v —— 计数器测试平台（testbench）
// 产生时钟/复位/使能，打印关键事件，并用 $dumpvars 导出 VCD。
`timescale 1ns/1ps

module counter_tb;

    reg        clk;
    reg        rst_n;
    reg        en;
    wire [3:0] count;

    // 例化被测设计（DUT）
    counter dut (
        .clk   (clk),
        .rst_n (rst_n),
        .en    (en),
        .count (count)
    );

    // 时钟：周期 10ns（每 5ns 翻转一次）
    initial clk = 1'b0;
    always #5 clk = ~clk;

    // 激励过程
    initial begin
        // VCD 导出：把 counter_tb 整个层级的信号写进 counter.vcd
        $dumpfile("out/counter.vcd");
        $dumpvars(0, counter_tb);

        rst_n = 1'b0; en = 1'b0;
        #12;                       // 保持复位 12ns
        rst_n = 1'b1;              // 撤复位
        $display("[%0t ns] release reset, count=%0d", $time, count);

        en = 1'b1;                 // 使能计数
        repeat (20) @(posedge clk);
        #1;
        $display("[%0t ns] after 20 enabled clocks, count=%0d", $time, count);

        en = 1'b0;                 // 暂停计数
        repeat (3) @(posedge clk);
        #1;
        $display("[%0t ns] paused 3 clocks, count=%0d (should hold)", $time, count);

        en = 1'b1;                 // 恢复计数，验证 4 位回绕
        repeat (5) @(posedge clk);
        #1;
        $display("[%0t ns] after 5 more clocks, count=%0d (wrap check)", $time, count);

        $display("[%0t ns] TEST PASS: counter works as expected", $time);
        $finish;
    end

    // 每个时钟沿打印一次计数值，便于对照 VCD
    always @(posedge clk) begin
        $display("[%0t ns] clk posedge: rst_n=%b en=%b count=%0d",
                 $time, rst_n, en, count);
    end

endmodule

experiments/eda-lab-wave-viewer-compare/counter.vcd
$date
	Wed Oct  7 14:57:18 2026
$end
$version
	Icarus Verilog
$end
$timescale
	1ps
$end
$scope module counter_tb $end
$var wire 4 ! count [3:0] $end
$var reg 1 " clk $end
$var reg 1 # en $end
$var reg 1 $ rst_n $end
$scope module dut $end
$var wire 1 " clk $end
$var wire 1 # en $end
$var wire 1 $ rst_n $end
$var reg 4 % count [3:0] $end
$upscope $end
$upscope $end
$enddefinitions $end
$comment Show the parameter values. $end
$dumpall
$end
#0
$dumpvars
bx %
0$
0#
0"
bx !
$end
#5000
b0 !
b0 %
1"
#10000
0"
#12000
1#
1$
#15000
b1 !
b1 %
1"
#20000
0"
#25000
b10 !
b10 %
1"
#30000
0"
#35000
b11 !
b11 %
1"
#40000
0"
#45000
b100 !
b100 %
1"
#50000
0"
#55000
b101 !
b101 %
1"
#60000
0"
#65000
b110 !
b110 %
1"
#70000
0"
#75000
b111 !
b111 %
1"
#80000
0"
#85000
b1000 !
b1000 %
1"
#90000
0"
#95000
b1001 !
b1001 %
1"
#100000
0"
#105000
b1010 !
b1010 %
1"
#110000
0"
#115000
b1011 !
b1011 %
1"
#120000
0"
#125000
b1100 !
b1100 %
1"
#130000
0"
#135000
b1101 !
b1101 %
1"
#140000
0"
#145000
b1110 !
b1110 %
1"
#150000
0"
#155000
b1111 !
b1111 %
1"
#160000
0"
#165000
b0 !
b0 %
1"
#170000
0"
#175000
b1 !
b1 %
1"
#180000
0"
#185000
b10 !
b10 %
1"
#190000
0"
#195000
b11 !
b11 %
1"
#200000
0"
#205000
b100 !
b100 %
1"
#206000
0#
#210000
0"
#215000
1"
#220000
0"
#225000
1"
#230000
0"
#235000
1"
#236000
1#
#240000
0"
#245000
b101 !
b101 %
1"
#250000
0"
#255000
b110 !
b110 %
1"
#260000
0"
#265000
b111 !
b111 %
1"
#270000
0"
#275000
b1000 !
b1000 %
1"
#280000
0"
#285000
b1001 !
b1001 %
1"
